bin/document_schemas.py
docs/conf.py
docs/technical_reference/edb/schemas/component.json
docs/technical_reference/edb/schemas/reaction.json
examples/edb/carbonic_acid_example.py
proteuslib/__init__.py
proteuslib/conftest.py
proteuslib/edb/__init__.py
proteuslib/edb/commands.py
proteuslib/edb/data_model.py
proteuslib/edb/db_api.py
proteuslib/edb/error.py
proteuslib/edb/schemas.py
proteuslib/edb/validate.py
proteuslib/edb/data/base.json
proteuslib/edb/data/component.json
proteuslib/edb/data/reaction.json
proteuslib/edb/tests/__init__.py
proteuslib/edb/tests/data.py
proteuslib/edb/tests/test_data_model.py
proteuslib/edb/tests/test_db_api.py
proteuslib/edb/tests/test_edb.py
proteuslib/edb/tests/test_schemas.py
proteuslib/edb/tests/test_validate.py
proteuslib/edb/tests/util.py
proteuslib/flowsheets/__init__.py
proteuslib/flowsheets/RO_with_energy_recovery/RO_with_energy_recovery.py
proteuslib/flowsheets/RO_with_energy_recovery/__init__.py
proteuslib/flowsheets/RO_with_energy_recovery/financials.py
proteuslib/flowsheets/RO_with_energy_recovery/monte_carlo_sampling_RO_ERD.py
proteuslib/flowsheets/RO_with_energy_recovery/tests/__init__.py
proteuslib/flowsheets/RO_with_energy_recovery/tests/test_RO_with_energy_recovery_simulation.py
proteuslib/flowsheets/RO_with_energy_recovery/tests/test_monte_carlo_sampling_RO_ERD.py
proteuslib/flowsheets/full_treatment_train/__init__.py
proteuslib/flowsheets/full_treatment_train/chemical_flowsheet_util.py
proteuslib/flowsheets/full_treatment_train/electrolyte_scaling_utils.py
proteuslib/flowsheets/full_treatment_train/util.py
proteuslib/flowsheets/full_treatment_train/analysis/__init__.py
proteuslib/flowsheets/full_treatment_train/analysis/flowsheet_NF.py
proteuslib/flowsheets/full_treatment_train/analysis/flowsheet_NF_no_bypass.py
proteuslib/flowsheets/full_treatment_train/analysis/flowsheet_NF_two_stage.py
proteuslib/flowsheets/full_treatment_train/analysis/flowsheet_single_stage.py
proteuslib-0.2.0.dist-info/LICENSE.md
proteuslib-0.2.0.dist-info/METADATA
proteuslib-0.2.0.dist-info/WHEEL
proteuslib-0.2.0.dist-info/entry_points.txt
proteuslib-0.2.0.dist-info/top_level.txt
proteuslib-0.2.0.dist-info/RECORD
