Metadata-Version: 2.1
Name: proteuslib
Version: 0.2.0
Summary: ProteusLib modeling library
Home-page: https://github.com/nawi-hub/proteuslib
Author: NAWI team
License: BSD
Keywords: water systems,chemical engineering,process modeling,filtration,desalination,nawi
Platform: UNKNOWN
Classifier: Development Status :: 3 - Alpha
Classifier: Intended Audience :: End Users/Desktop
Classifier: Intended Audience :: Science/Research
Classifier: License :: OSI Approved :: BSD License
Classifier: Natural Language :: English
Classifier: Operating System :: MacOS
Classifier: Operating System :: Microsoft :: Windows
Classifier: Operating System :: Unix
Classifier: Programming Language :: Python
Classifier: Programming Language :: Python :: 3
Classifier: Programming Language :: Python :: 3.6
Classifier: Programming Language :: Python :: 3.7
Classifier: Programming Language :: Python :: 3.8
Classifier: Programming Language :: Python :: Implementation :: CPython
Classifier: Topic :: Scientific/Engineering :: Mathematics
Classifier: Topic :: Scientific/Engineering :: Chemistry
Classifier: Topic :: Software Development :: Libraries :: Python Modules
Classifier: Programming Language :: Python :: 3 :: Only
Requires-Python: >=3.6, <4
License-File: LICENSE.md
Requires-Dist: idaes-pse (>=1.11.0)
Requires-Dist: pyomo
Requires-Dist: pymongo (>3)
Requires-Dist: fastjsonschema
Requires-Dist: click
Requires-Dist: nbformat
Requires-Dist: scipy
Requires-Dist: pywin32 (==225) ; platform_system == "Windows" and python_version >= "3.8"
Provides-Extra: dev
Requires-Dist: myst-parser ; extra == 'dev'
Requires-Dist: linkify-it-py ; extra == 'dev'
Requires-Dist: Sphinx ; extra == 'dev'
Requires-Dist: sphinx-rtd-theme ; extra == 'dev'
Requires-Dist: json-schema-for-humans ; extra == 'dev'
Requires-Dist: black ; extra == 'dev'
Requires-Dist: pytest ; extra == 'dev'
Requires-Dist: pytest-cov ; extra == 'dev'
Requires-Dist: mongomock ; extra == 'dev'
Provides-Extra: testing
Requires-Dist: pytest ; extra == 'testing'
Requires-Dist: json-schema-for-humans ; extra == 'testing'
Requires-Dist: mongomock ; extra == 'testing'
